cinegraph/__init__.py
cinegraph/cli.py
cinegraph/gradient.py
cinegraph/images.py
cinegraph/process.py
cinegraph/utils.py
cinegraph-0.2.2.dist-info/entry_points.txt
cinegraph-0.2.2.dist-info/LICENSE
cinegraph-0.2.2.dist-info/WHEEL
cinegraph-0.2.2.dist-info/METADATA
cinegraph-0.2.2.dist-info/RECORD
