Metadata-Version: 2.1
Name: cinegraph
Version: 0.2.2
Summary: A CLI tool that creates a kaleidescope-esque gradient image of your favorite movie.
Keywords: cinegraph,cinema,movie,gradient,opencv,cli,image,film,motiongraph,colors
Author: Andres Weber
Author-email: andresmweber@gmail.com
Requires-Python: >=3.8,<4.0
Classifier: Programming Language :: Python :: 3
Classifier: Programming Language :: Python :: 3.8
Classifier: Programming Language :: Python :: 3.9
Requires-Dist: fire (>=0.4.0,<0.5.0)
Requires-Dist: opencv-python (>=4.5.3,<5.0.0)
Requires-Dist: tqdm (>=4.62.1,<5.0.0)
